{"Nodes":[],"ExecutionTime":"2022-12-02T11:28:53.0642454Z","GenerationTime":"0001-01-01T00:00:00","PluginUserSpecFlowId":"db0be5a7-8e64-4e81-9995-397538608627","CLIUserSpecFlowId":null,"ExecutionResults":[{"ContextType":"Scenario","FeatureFolderPath":"Features","FeatureTitle":"Login","ScenarioTitle":"Failed login when both fields are invalid","ScenarioArguments":[],"Status":"OK","StepResults":[{"Duration":"00:00:10.5651077","Status":"OK","Error":null,"Outputs":null},{"Duration":"00:00:00.1014992","Status":"OK","Error":null,"Outputs":null},{"Duration":"00:00:00.0343056","Status":"OK","Error":null,"Outputs":null},{"Duration":"00:00:00.6258840","Status":"OK","Error":null,"Outputs":null}],"Outputs":null},{"ContextType":"Scenario","FeatureFolderPath":"Features","FeatureTitle":"Login","ScenarioTitle":"Failed login when username is incorrect and password is correct","ScenarioArguments":[],"Status":"OK","StepResults":[{"Duration":"00:00:10.8935200","Status":"OK","Error":null,"Outputs":null},{"Duration":"00:00:00.0955513","Status":"OK","Error":null,"Outputs":null},{"Duration":"00:00:00.0404623","Status":"OK","Error":null,"Outputs":null},{"Duration":"00:00:00.6448383","Status":"OK","Error":null,"Outputs":null}],"Outputs":null},{"ContextType":"Scenario","FeatureFolderPath":"Features","FeatureTitle":"Login","ScenarioTitle":"Failed login when both fields are empty","ScenarioArguments":[],"Status":"OK","StepResults":[{"Duration":"00:00:08.6600253","Status":"OK","Error":null,"Outputs":null},{"Duration":"00:00:00.0739068","Status":"OK","Error":null,"Outputs":null},{"Duration":"00:00:00.0311306","Status":"OK","Error":null,"Outputs":null},{"Duration":"00:00:00.2347531","Status":"OK","Error":null,"Outputs":[{"OutputLocation":"Step","Type":"Text","Message":"rgb(220, 53, 69)","FilePath":null}]},{"Duration":"00:00:00.3201210","Status":"OK","Error":null,"Outputs":[{"OutputLocation":"Step","Type":"Text","Message":"rgb(220, 53, 69)","FilePath":null}]}],"Outputs":null},{"ContextType":"Scenario","FeatureFolderPath":"Features","FeatureTitle":"Login","ScenarioTitle":"Failed login when username is correct and password is empty","ScenarioArguments":[],"Status":"OK","StepResults":[{"Duration":"00:00:07.9531880","Status":"OK","Error":null,"Outputs":null},{"Duration":"00:00:00.0807982","Status":"OK","Error":null,"Outputs":null},{"Duration":"00:00:00.0267845","Status":"OK","Error":null,"Outputs":null},{"Duration":"00:00:00.3446418","Status":"OK","Error":null,"Outputs":[{"OutputLocation":"Step","Type":"Text","Message":"rgb(220, 53, 69)","FilePath":null}]}],"Outputs":null},{"ContextType":"Scenario","FeatureFolderPath":"Features","FeatureTitle":"Login","ScenarioTitle":"Failed login when username is correct and password is incorrect","ScenarioArguments":[],"Status":"OK","StepResults":[{"Duration":"00:00:07.1392757","Status":"OK","Error":null,"Outputs":null},{"Duration":"00:00:00.0862533","Status":"OK","Error":null,"Outputs":null},{"Duration":"00:00:00.0369621","Status":"OK","Error":null,"Outputs":null},{"Duration":"00:00:00.6300373","Status":"OK","Error":null,"Outputs":null}],"Outputs":null},{"ContextType":"Scenario","FeatureFolderPath":"Features","FeatureTitle":"Login","ScenarioTitle":"Successful login with valid credentials","ScenarioArguments":["testuser_1","Test@123"],"Status":"OK","StepResults":[{"Duration":"00:00:06.6773140","Status":"OK","Error":null,"Outputs":null},{"Duration":"00:00:00.1005936","Status":"OK","Error":null,"Outputs":null},{"Duration":"00:00:00.0375405","Status":"OK","Error":null,"Outputs":null},{"Duration":"00:00:01.0964390","Status":"OK","Error":null,"Outputs":[{"OutputLocation":"Step","Type":"Text","Message":"https://demoqa.com/profile","FilePath":null}]}],"Outputs":null},{"ContextType":"Scenario","FeatureFolderPath":"Features","FeatureTitle":"Login","ScenarioTitle":"Successful login with valid credentials","ScenarioArguments":["testuser","Test@123"],"Status":"OK","StepResults":[{"Duration":"00:00:07.7991198","Status":"OK","Error":null,"Outputs":null},{"Duration":"00:00:00.0956617","Status":"OK","Error":null,"Outputs":null},{"Duration":"00:00:00.0311873","Status":"OK","Error":null,"Outputs":null},{"Duration":"00:00:01.1318477","Status":"OK","Error":null,"Outputs":[{"OutputLocation":"Step","Type":"Text","Message":"https://demoqa.com/profile","FilePath":null}]}],"Outputs":null},{"ContextType":"Scenario","FeatureFolderPath":"Features","FeatureTitle":"Login","ScenarioTitle":"Successful login with valid credentials","ScenarioArguments":["laiba123","Laiba@123"],"Status":"OK","StepResults":[{"Duration":"00:00:06.9173569","Status":"OK","Error":null,"Outputs":null},{"Duration":"00:00:00.0932926","Status":"OK","Error":null,"Outputs":null},{"Duration":"00:00:00.0340967","Status":"OK","Error":null,"Outputs":null},{"Duration":"00:00:01.1250959","Status":"OK","Error":null,"Outputs":[{"OutputLocation":"Step","Type":"Text","Message":"https://demoqa.com/profile","FilePath":null}]}],"Outputs":null},{"ContextType":"Scenario","FeatureFolderPath":"Features","FeatureTitle":"Login","ScenarioTitle":"Failed login when username is empty and password is correct","ScenarioArguments":[],"Status":"OK","StepResults":[{"Duration":"00:00:08.2868220","Status":"OK","Error":null,"Outputs":null},{"Duration":"00:00:00.0852420","Status":"OK","Error":null,"Outputs":null},{"Duration":"00:00:00.0332517","Status":"OK","Error":null,"Outputs":null},{"Duration":"00:00:00.2426904","Status":"OK","Error":null,"Outputs":[{"OutputLocation":"Step","Type":"Text","Message":"rgb(220, 53, 69)","FilePath":null}]}],"Outputs":null}],"StepReports":null}